netvulnscan/__init__.py
netvulnscan/__main__.py
netvulnscan/netdev_discovery.py
netvulnscan/netdev_scan.py
netvulnscan/netdev_vuln.py
netvulnscan-0.1.2.dist-info/LICENSE
netvulnscan-0.1.2.dist-info/METADATA
netvulnscan-0.1.2.dist-info/WHEEL
netvulnscan-0.1.2.dist-info/top_level.txt
netvulnscan-0.1.2.dist-info/RECORD
