Metadata-Version: 2.1
Name: netvulnscan
Version: 0.1.2
Summary: A package to discover network devices, scan ports and services, and find vulnerabilities.
Home-page: https://github.com/Hr12aNe/NetVulnScan
Author: Hrishikesh Rane
Author-email: rishirane1204@gmail.com
Classifier: Programming Language :: Python :: 3
Classifier: License :: OSI Approved :: MIT License
Classifier: Operating System :: OS Independent
Requires-Python: >=3.6
License-File: LICENSE
Requires-Dist: python-nmap ==0.7.1
Requires-Dist: requests ==2.31.0
Requires-Dist: scapy ==2.4.5
